{
    "intersystems_payer_services_hp_pas":{
        "interopCredentials":[
            {
                "identifier":"pasUmCreds",
                "userName":"testuser2",
                "password":"abc1234"
            }
        ],
        "sslConfigs":[
            {
                "name":"ISC.FeatureTracker.SSL.Config",
                "description":"For contacting OAuth server for PAS",
                "verifyPeer":false,
                "privateKeyType":"RSA",
                "tlsMaxVersion":"TLSv1.3",
                "tlsMinVersion":"TLSv1.2",
                "ocsp":false
            },
            {
                "name":"LocalUMConfig",
                "description":"For contacting local UM server",
                "verifyPeer":false,
                "privateKeyType":"RSA",
                "tlsMaxVersion":"TLSv1.3",
                "tlsMinVersion":"TLSv1.2",
                "ocsp":false
            }
        ],
        "httpServices":[
            {
                "name":"PAS|SUBMIT",
                "host":"usp5570qxie.iscinternal.com",
                "port":3000,
                "url":"/claim",
                "sslConfig":"ISC.FeatureTracker.SSL.Config",
                "httpCredentialsConfig":"pasUmCreds",
                "authType": "basic"
            },
            {
                "name":"PAS|INQUIRE",
                "host":"usp5570qxie.iscinternal.com",
                "port":3000,
                "url":"/claim",
                "sslConfig":"ISC.FeatureTracker.SSL.Config",
                "httpCredentialsConfig":"pasUmCreds",
                "authType": "basic"
            },
            {
                "name":"PAS|SUBSCRIPTION",
                "host":"usp5570qxie.iscinternal.com",
                "port":3002,
                "url":"/claim",
                "sslConfig":"ISC.FeatureTracker.SSL.Config",
                "httpCredentialsConfig":"pasUmCreds",
                "authType": "basic"
            }
        ],
        "oAuthServerConfigs":[
            {
                "oAuthServerEndpoint":"https://dev-13926970.okta.com/oauth2/auskb8z8bmtLfjE4X5d7",
                "oAuthServerSSLConfig":"ISC.FeatureTracker.SSL.Config",
                "clients":[
                    {
                        "clientName":"PASResourceServer",
                        "clientType":"resource",
                        "sslConfiguration":"ISC.FeatureTracker.SSL.Config",
                        "clientCredentialsID":"0oakxk8nxcCVDSVsN5d7",
                        "clientSecret":"Ig8N6NOflUSH4iPz0bvuzX1Dnu5n_EPzeN4SCDM-nNUu9VeMlgVdcTAq35cMqJ6K"
                    }
                ]
            },
            {
                "oAuthServerEndpoint":"https://dev-13206116.okta.com/oauth2/default",
                "oAuthServerSSLConfig":"ISC.FeatureTracker.SSL.Config",
                "clients":[
                    {
                        "clientName":"UMClient",
                        "redirectUrlHost":"",
                        "redirectUrlPort":"",
                        "clientCredentialsID":"C4VUHY_SyjlWra6iqi7Y-FryzetuxlN9J7AhL2MU23U",
                        "clientSecret":"VbS1Rh_OCSrzjyRkdAy0b7s4IeAQSoKrWqezwDG34SHZouQtHRrsQ7XpxAGFSDbwTn5m3TR67OEJwGCvk86v_w",
                        "clientType":"confidential",
                        "sslConfiguration":"LocalUMConfig"
                    }
                ]
            }
        ],
        "productionSettings": {
            "productionName": "HS.HP.PAS.Local.Production",
            "settings": [
                {
                    "settingName": "EnableX12Transform",
                    "settingValue": "1",
                    "target": "Production"
                },
                {
                    "settingName": "SSLCheckServerIdentity",
                    "settingValue": "1",
                    "target": "Production"
                },
                {
                    "settingName": "LogRequestResponse",
                    "settingValue": "0",
                    "target": "Production"
                },
                {
                    "settingName": "UseMockUp",
                    "settingValue": "0",
                    "target": "Production"
                }
            ],
            "items": [
                {
                    "name": "PollingService",
                    "settings": [
                        {
                            "settingName": "Enabled",
                            "settingValue": "1",
                            "target": "Item"
                        },
                        {
                            "settingName": "CallInterval",
                            "settingValue": "300",
                            "target": "Adapter"
                        }
                   ]
               }
            ]
        }
    }
}
